LICENSE
MANIFEST.in
README.md
setup.py
wgetdb.py
wgetdb.egg-info/PKG-INFO
wgetdb.egg-info/SOURCES.txt
wgetdb.egg-info/dependency_links.txt
wgetdb.egg-info/entry_points.txt
wgetdb.egg-info/not-zip-safe
wgetdb.egg-info/requires.txt
wgetdb.egg-info/top_level.txt