Metadata-Version: 1.1
Name: wgetdb
Version: 0.1.2
Summary: Download and store webpages in a sqlite database
Home-page: https://github.com/akiraak/wgetdb
Author: Akira Kozakai
Author-email: akiraak@gmail.com
License: Copyright 2013 Akira Kozakai
